{
    "type": "FeatureCollection",
    "features": [
        {
            "type": "Feature",
            "geometry": {
                "type": "Point",
                "coordinates": [
                    "73.542131",
                    "16.363557"
                ]
            },
            "properties": {
                "id": "39f783424a3bedf031a517f48350f124",
                "index": 0,
                "isActive": true,
                "logo": "thumbnail.png",
                "image": "thumbnail.png",
                "link": "https://sindhudurg.mapodiary.com/general/sai-samarth-clinic/2439",
                "url": "",
                "name": "SAI SAMARTH CLINIC",
                "category": "general",
                "email": "",
                "stars": "0.0",
                "phone": "9823095608",
                "address": "H.No.512/A Pan bajar Near Babachand Darga, opp. Maratha Cloth Stores, Kudal, Maharashtra 416520rn",
                "about": "about",
                "tags": [
                    ""
                ]
            }
        }
    ]
}