{
    "type": "FeatureCollection",
    "features": [
        {
            "type": "Feature",
            "geometry": {
                "type": "Point",
                "coordinates": [
                    "73.55516",
                    "16.355621"
                ]
            },
            "properties": {
                "id": "7be15f1113b3dc1f3d4f03245e6dc94b",
                "index": 0,
                "isActive": true,
                "logo": "thumbnail.png",
                "image": "thumbnail.png",
                "link": "https://sindhudurg.mapodiary.com/general/om-shree-solution/2046",
                "url": "",
                "name": "Om Shree Solution",
                "category": "general",
                "email": "",
                "stars": "0.0",
                "phone": "9890508695",
                "address": "Shop no 93 /1 , Madhala wada, Agarwada C/o Omkar Phatak, Pernem, Goa 403512rn",
                "about": "about",
                "tags": [
                    ""
                ]
            }
        }
    ]
}